{"CinderVolumeTypes.create_and_delete_volume_type": [{"runner": {"times": 2000, "type": "constant", "concurrency": 5}, "args": {}, "sla": {"failure_rate": {"max": 0}, "max_avg_duration": 3.0, "max_seconds_per_iteration": 5.0}, "context": {"users": {"tenants": 3, "users_per_tenant": 5}}}, {"runner": {"times": 2000, "type": "constant", "concurrency": 6}, "args": {}, "sla": {"failure_rate": {"max": 0}, "max_avg_duration": 3.0, "max_seconds_per_iteration": 5.0}, "context": {"users": {"tenants": 3, "users_per_tenant": 5}}}, {"runner": {"times": 2000, "type": "constant", "concurrency": 7}, "args": {}, "sla": {"failure_rate": {"max": 0}, "max_avg_duration": 3.0, "max_seconds_per_iteration": 5.0}, "context": {"users": {"tenants": 3, "users_per_tenant": 5}}}, {"runner": {"times": 2000, "type": "constant", "concurrency": 8}, "args": {}, "sla": {"failure_rate": {"max": 0}, "max_avg_duration": 3.0, "max_seconds_per_iteration": 5.0}, "context": {"users": {"tenants": 3, "users_per_tenant": 5}}}, {"runner": {"times": 2000, "type": "constant", "concurrency": 9}, "args": {}, "sla": {"failure_rate": {"max": 0}, "max_avg_duration": 3.0, "max_seconds_per_iteration": 5.0}, "context": {"users": {"tenants": 3, "users_per_tenant": 5}}}, {"runner": {"times": 2000, "type": "constant", "concurrency": 10}, "args": {}, "sla": {"failure_rate": {"max": 0}, "max_avg_duration": 3.0, "max_seconds_per_iteration": 5.0}, "context": {"users": {"tenants": 3, "users_per_tenant": 5}}}, {"runner": {"times": 2000, "type": "constant", "concurrency": 11}, "args": {}, "sla": {"failure_rate": {"max": 0}, "max_avg_duration": 3.0, "max_seconds_per_iteration": 5.0}, "context": {"users": {"tenants": 3, "users_per_tenant": 5}}}, {"runner": {"times": 2000, "type": "constant", "concurrency": 12}, "args": {}, "sla": {"failure_rate": {"max": 0}, "max_avg_duration": 3.0, "max_seconds_per_iteration": 5.0}, "context": {"users": {"tenants": 3, "users_per_tenant": 5}}}, {"runner": {"times": 2000, "type": "constant", "concurrency": 13}, "args": {}, "sla": {"failure_rate": {"max": 0}, "max_avg_duration": 3.0, "max_seconds_per_iteration": 5.0}, "context": {"users": {"tenants": 3, "users_per_tenant": 5}}}, {"runner": {"times": 2000, "type": "constant", "concurrency": 14}, "args": {}, "sla": {"failure_rate": {"max": 0}, "max_avg_duration": 3.0, "max_seconds_per_iteration": 5.0}, "context": {"users": {"tenants": 3, "users_per_tenant": 5}}}, {"runner": {"times": 2000, "type": "constant", "concurrency": 15}, "args": {}, "sla": {"failure_rate": {"max": 0}, "max_avg_duration": 3.0, "max_seconds_per_iteration": 5.0}, "context": {"users": {"tenants": 3, "users_per_tenant": 5}}}, {"runner": {"times": 2000, "type": "constant", "concurrency": 16}, "args": {}, "sla": {"failure_rate": {"max": 0}, "max_avg_duration": 3.0, "max_seconds_per_iteration": 5.0}, "context": {"users": {"tenants": 3, "users_per_tenant": 5}}}, {"runner": {"times": 2000, "type": "constant", "concurrency": 17}, "args": {}, "sla": {"failure_rate": {"max": 0}, "max_avg_duration": 3.0, "max_seconds_per_iteration": 5.0}, "context": {"users": {"tenants": 3, "users_per_tenant": 5}}}, {"runner": {"times": 2000, "type": "constant", "concurrency": 18}, "args": {}, "sla": {"failure_rate": {"max": 0}, "max_avg_duration": 3.0, "max_seconds_per_iteration": 5.0}, "context": {"users": {"tenants": 3, "users_per_tenant": 5}}}, {"runner": {"times": 2000, "type": "constant", "concurrency": 19}, "args": {}, "sla": {"failure_rate": {"max": 0}, "max_avg_duration": 3.0, "max_seconds_per_iteration": 5.0}, "context": {"users": {"tenants": 3, "users_per_tenant": 5}}}, {"runner": {"times": 2000, "type": "constant", "concurrency": 20}, "args": {}, "sla": {"failure_rate": {"max": 0}, "max_avg_duration": 3.0, "max_seconds_per_iteration": 5.0}, "context": {"users": {"tenants": 3, "users_per_tenant": 5}}}, {"runner": {"times": 2000, "type": "constant", "concurrency": 21}, "args": {}, "sla": {"failure_rate": {"max": 0}, "max_avg_duration": 3.0, "max_seconds_per_iteration": 5.0}, "context": {"users": {"tenants": 3, "users_per_tenant": 5}}}, {"runner": {"times": 2000, "type": "constant", "concurrency": 22}, "args": {}, "sla": {"failure_rate": {"max": 0}, "max_avg_duration": 3.0, "max_seconds_per_iteration": 5.0}, "context": {"users": {"tenants": 3, "users_per_tenant": 5}}}, {"runner": {"times": 2000, "type": "constant", "concurrency": 23}, "args": {}, "sla": {"failure_rate": {"max": 0}, "max_avg_duration": 3.0, "max_seconds_per_iteration": 5.0}, "context": {"users": {"tenants": 3, "users_per_tenant": 5}}}, {"runner": {"times": 2000, "type": "constant", "concurrency": 24}, "args": {}, "sla": {"failure_rate": {"max": 0}, "max_avg_duration": 3.0, "max_seconds_per_iteration": 5.0}, "context": {"users": {"tenants": 3, "users_per_tenant": 5}}}, {"runner": {"times": 2000, "type": "constant", "concurrency": 25}, "args": {}, "sla": {"failure_rate": {"max": 0}, "max_avg_duration": 3.0, "max_seconds_per_iteration": 5.0}, "context": {"users": {"tenants": 3, "users_per_tenant": 5}}}, {"runner": {"times": 2000, "type": "constant", "concurrency": 26}, "args": {}, "sla": {"failure_rate": {"max": 0}, "max_avg_duration": 3.0, "max_seconds_per_iteration": 5.0}, "context": {"users": {"tenants": 3, "users_per_tenant": 5}}}, {"runner": {"times": 2000, "type": "constant", "concurrency": 27}, "args": {}, "sla": {"failure_rate": {"max": 0}, "max_avg_duration": 3.0, "max_seconds_per_iteration": 5.0}, "context": {"users": {"tenants": 3, "users_per_tenant": 5}}}, {"runner": {"times": 2000, "type": "constant", "concurrency": 28}, "args": {}, "sla": {"failure_rate": {"max": 0}, "max_avg_duration": 3.0, "max_seconds_per_iteration": 5.0}, "context": {"users": {"tenants": 3, "users_per_tenant": 5}}}, {"runner": {"times": 2000, "type": "constant", "concurrency": 29}, "args": {}, "sla": {"failure_rate": {"max": 0}, "max_avg_duration": 3.0, "max_seconds_per_iteration": 5.0}, "context": {"users": {"tenants": 3, "users_per_tenant": 5}}}, {"runner": {"times": 2000, "type": "constant", "concurrency": 30}, "args": {}, "sla": {"failure_rate": {"max": 0}, "max_avg_duration": 3.0, "max_seconds_per_iteration": 5.0}, "context": {"users": {"tenants": 3, "users_per_tenant": 5}}}, {"runner": {"times": 2000, "type": "constant", "concurrency": 31}, "args": {}, "sla": {"failure_rate": {"max": 0}, "max_avg_duration": 3.0, "max_seconds_per_iteration": 5.0}, "context": {"users": {"tenants": 3, "users_per_tenant": 5}}}, {"runner": {"times": 2000, "type": "constant", "concurrency": 32}, "args": {}, "sla": {"failure_rate": {"max": 0}, "max_avg_duration": 3.0, "max_seconds_per_iteration": 5.0}, "context": {"users": {"tenants": 3, "users_per_tenant": 5}}}, {"runner": {"times": 2000, "type": "constant", "concurrency": 33}, "args": {}, "sla": {"failure_rate": {"max": 0}, "max_avg_duration": 3.0, "max_seconds_per_iteration": 5.0}, "context": {"users": {"tenants": 3, "users_per_tenant": 5}}}, {"runner": {"times": 2000, "type": "constant", "concurrency": 34}, "args": {}, "sla": {"failure_rate": {"max": 0}, "max_avg_duration": 3.0, "max_seconds_per_iteration": 5.0}, "context": {"users": {"tenants": 3, "users_per_tenant": 5}}}, {"runner": {"times": 2000, "type": "constant", "concurrency": 35}, "args": {}, "sla": {"failure_rate": {"max": 0}, "max_avg_duration": 3.0, "max_seconds_per_iteration": 5.0}, "context": {"users": {"tenants": 3, "users_per_tenant": 5}}}, {"runner": {"times": 2000, "type": "constant", "concurrency": 36}, "args": {}, "sla": {"failure_rate": {"max": 0}, "max_avg_duration": 3.0, "max_seconds_per_iteration": 5.0}, "context": {"users": {"tenants": 3, "users_per_tenant": 5}}}, {"runner": {"times": 2000, "type": "constant", "concurrency": 37}, "args": {}, "sla": {"failure_rate": {"max": 0}, "max_avg_duration": 3.0, "max_seconds_per_iteration": 5.0}, "context": {"users": {"tenants": 3, "users_per_tenant": 5}}}, {"runner": {"times": 2000, "type": "constant", "concurrency": 38}, "args": {}, "sla": {"failure_rate": {"max": 0}, "max_avg_duration": 3.0, "max_seconds_per_iteration": 5.0}, "context": {"users": {"tenants": 3, "users_per_tenant": 5}}}, {"runner": {"times": 2000, "type": "constant", "concurrency": 39}, "args": {}, "sla": {"failure_rate": {"max": 0}, "max_avg_duration": 3.0, "max_seconds_per_iteration": 5.0}, "context": {"users": {"tenants": 3, "users_per_tenant": 5}}}, {"runner": {"times": 2000, "type": "constant", "concurrency": 40}, "args": {}, "sla": {"failure_rate": {"max": 0}, "max_avg_duration": 3.0, "max_seconds_per_iteration": 5.0}, "context": {"users": {"tenants": 3, "users_per_tenant": 5}}}, {"runner": {"times": 2000, "type": "constant", "concurrency": 41}, "args": {}, "sla": {"failure_rate": {"max": 0}, "max_avg_duration": 3.0, "max_seconds_per_iteration": 5.0}, "context": {"users": {"tenants": 3, "users_per_tenant": 5}}}, {"runner": {"times": 2000, "type": "constant", "concurrency": 42}, "args": {}, "sla": {"failure_rate": {"max": 0}, "max_avg_duration": 3.0, "max_seconds_per_iteration": 5.0}, "context": {"users": {"tenants": 3, "users_per_tenant": 5}}}, {"runner": {"times": 2000, "type": "constant", "concurrency": 43}, "args": {}, "sla": {"failure_rate": {"max": 0}, "max_avg_duration": 3.0, "max_seconds_per_iteration": 5.0}, "context": {"users": {"tenants": 3, "users_per_tenant": 5}}}, {"runner": {"times": 2000, "type": "constant", "concurrency": 44}, "args": {}, "sla": {"failure_rate": {"max": 0}, "max_avg_duration": 3.0, "max_seconds_per_iteration": 5.0}, "context": {"users": {"tenants": 3, "users_per_tenant": 5}}}, {"runner": {"times": 2000, "type": "constant", "concurrency": 45}, "args": {}, "sla": {"failure_rate": {"max": 0}, "max_avg_duration": 3.0, "max_seconds_per_iteration": 5.0}, "context": {"users": {"tenants": 3, "users_per_tenant": 5}}}, {"runner": {"times": 2000, "type": "constant", "concurrency": 46}, "args": {}, "sla": {"failure_rate": {"max": 0}, "max_avg_duration": 3.0, "max_seconds_per_iteration": 5.0}, "context": {"users": {"tenants": 3, "users_per_tenant": 5}}}, {"runner": {"times": 2000, "type": "constant", "concurrency": 47}, "args": {}, "sla": {"failure_rate": {"max": 0}, "max_avg_duration": 3.0, "max_seconds_per_iteration": 5.0}, "context": {"users": {"tenants": 3, "users_per_tenant": 5}}}, {"runner": {"times": 2000, "type": "constant", "concurrency": 48}, "args": {}, "sla": {"failure_rate": {"max": 0}, "max_avg_duration": 3.0, "max_seconds_per_iteration": 5.0}, "context": {"users": {"tenants": 3, "users_per_tenant": 5}}}, {"runner": {"times": 2000, "type": "constant", "concurrency": 49}, "args": {}, "sla": {"failure_rate": {"max": 0}, "max_avg_duration": 3.0, "max_seconds_per_iteration": 5.0}, "context": {"users": {"tenants": 3, "users_per_tenant": 5}}}, {"runner": {"times": 2000, "type": "constant", "concurrency": 50}, "args": {}, "sla": {"failure_rate": {"max": 0}, "max_avg_duration": 3.0, "max_seconds_per_iteration": 5.0}, "context": {"users": {"tenants": 3, "users_per_tenant": 5}}}, {"runner": {"times": 2000, "type": "constant", "concurrency": 51}, "args": {}, "sla": {"failure_rate": {"max": 0}, "max_avg_duration": 3.0, "max_seconds_per_iteration": 5.0}, "context": {"users": {"tenants": 3, "users_per_tenant": 5}}}, {"runner": {"times": 2000, "type": "constant", "concurrency": 52}, "args": {}, "sla": {"failure_rate": {"max": 0}, "max_avg_duration": 3.0, "max_seconds_per_iteration": 5.0}, "context": {"users": {"tenants": 3, "users_per_tenant": 5}}}, {"runner": {"times": 2000, "type": "constant", "concurrency": 53}, "args": {}, "sla": {"failure_rate": {"max": 0}, "max_avg_duration": 3.0, "max_seconds_per_iteration": 5.0}, "context": {"users": {"tenants": 3, "users_per_tenant": 5}}}, {"runner": {"times": 2000, "type": "constant", "concurrency": 54}, "args": {}, "sla": {"failure_rate": {"max": 0}, "max_avg_duration": 3.0, "max_seconds_per_iteration": 5.0}, "context": {"users": {"tenants": 3, "users_per_tenant": 5}}}, {"runner": {"times": 2000, "type": "constant", "concurrency": 55}, "args": {}, "sla": {"failure_rate": {"max": 0}, "max_avg_duration": 3.0, "max_seconds_per_iteration": 5.0}, "context": {"users": {"tenants": 3, "users_per_tenant": 5}}}, {"runner": {"times": 2000, "type": "constant", "concurrency": 56}, "args": {}, "sla": {"failure_rate": {"max": 0}, "max_avg_duration": 3.0, "max_seconds_per_iteration": 5.0}, "context": {"users": {"tenants": 3, "users_per_tenant": 5}}}, {"runner": {"times": 2000, "type": "constant", "concurrency": 57}, "args": {}, "sla": {"failure_rate": {"max": 0}, "max_avg_duration": 3.0, "max_seconds_per_iteration": 5.0}, "context": {"users": {"tenants": 3, "users_per_tenant": 5}}}, {"runner": {"times": 2000, "type": "constant", "concurrency": 58}, "args": {}, "sla": {"failure_rate": {"max": 0}, "max_avg_duration": 3.0, "max_seconds_per_iteration": 5.0}, "context": {"users": {"tenants": 3, "users_per_tenant": 5}}}, {"runner": {"times": 2000, "type": "constant", "concurrency": 59}, "args": {}, "sla": {"failure_rate": {"max": 0}, "max_avg_duration": 3.0, "max_seconds_per_iteration": 5.0}, "context": {"users": {"tenants": 3, "users_per_tenant": 5}}}, {"runner": {"times": 2000, "type": "constant", "concurrency": 60}, "args": {}, "sla": {"failure_rate": {"max": 0}, "max_avg_duration": 3.0, "max_seconds_per_iteration": 5.0}, "context": {"users": {"tenants": 3, "users_per_tenant": 5}}}, {"runner": {"times": 2000, "type": "constant", "concurrency": 61}, "args": {}, "sla": {"failure_rate": {"max": 0}, "max_avg_duration": 3.0, "max_seconds_per_iteration": 5.0}, "context": {"users": {"tenants": 3, "users_per_tenant": 5}}}, {"runner": {"times": 2000, "type": "constant", "concurrency": 62}, "args": {}, "sla": {"failure_rate": {"max": 0}, "max_avg_duration": 3.0, "max_seconds_per_iteration": 5.0}, "context": {"users": {"tenants": 3, "users_per_tenant": 5}}}, {"runner": {"times": 2000, "type": "constant", "concurrency": 63}, "args": {}, "sla": {"failure_rate": {"max": 0}, "max_avg_duration": 3.0, "max_seconds_per_iteration": 5.0}, "context": {"users": {"tenants": 3, "users_per_tenant": 5}}}, {"runner": {"times": 2000, "type": "constant", "concurrency": 64}, "args": {}, "sla": {"failure_rate": {"max": 0}, "max_avg_duration": 3.0, "max_seconds_per_iteration": 5.0}, "context": {"users": {"tenants": 3, "users_per_tenant": 5}}}, {"runner": {"times": 2000, "type": "constant", "concurrency": 65}, "args": {}, "sla": {"failure_rate": {"max": 0}, "max_avg_duration": 3.0, "max_seconds_per_iteration": 5.0}, "context": {"users": {"tenants": 3, "users_per_tenant": 5}}}, {"runner": {"times": 2000, "type": "constant", "concurrency": 66}, "args": {}, "sla": {"failure_rate": {"max": 0}, "max_avg_duration": 3.0, "max_seconds_per_iteration": 5.0}, "context": {"users": {"tenants": 3, "users_per_tenant": 5}}}, {"runner": {"times": 2000, "type": "constant", "concurrency": 67}, "args": {}, "sla": {"failure_rate": {"max": 0}, "max_avg_duration": 3.0, "max_seconds_per_iteration": 5.0}, "context": {"users": {"tenants": 3, "users_per_tenant": 5}}}, {"runner": {"times": 2000, "type": "constant", "concurrency": 68}, "args": {}, "sla": {"failure_rate": {"max": 0}, "max_avg_duration": 3.0, "max_seconds_per_iteration": 5.0}, "context": {"users": {"tenants": 3, "users_per_tenant": 5}}}, {"runner": {"times": 2000, "type": "constant", "concurrency": 69}, "args": {}, "sla": {"failure_rate": {"max": 0}, "max_avg_duration": 3.0, "max_seconds_per_iteration": 5.0}, "context": {"users": {"tenants": 3, "users_per_tenant": 5}}}, {"runner": {"times": 2000, "type": "constant", "concurrency": 70}, "args": {}, "sla": {"failure_rate": {"max": 0}, "max_avg_duration": 3.0, "max_seconds_per_iteration": 5.0}, "context": {"users": {"tenants": 3, "users_per_tenant": 5}}}, {"runner": {"times": 2000, "type": "constant", "concurrency": 71}, "args": {}, "sla": {"failure_rate": {"max": 0}, "max_avg_duration": 3.0, "max_seconds_per_iteration": 5.0}, "context": {"users": {"tenants": 3, "users_per_tenant": 5}}}, {"runner": {"times": 2000, "type": "constant", "concurrency": 72}, "args": {}, "sla": {"failure_rate": {"max": 0}, "max_avg_duration": 3.0, "max_seconds_per_iteration": 5.0}, "context": {"users": {"tenants": 3, "users_per_tenant": 5}}}, {"runner": {"times": 2000, "type": "constant", "concurrency": 73}, "args": {}, "sla": {"failure_rate": {"max": 0}, "max_avg_duration": 3.0, "max_seconds_per_iteration": 5.0}, "context": {"users": {"tenants": 3, "users_per_tenant": 5}}}, {"runner": {"times": 2000, "type": "constant", "concurrency": 74}, "args": {}, "sla": {"failure_rate": {"max": 0}, "max_avg_duration": 3.0, "max_seconds_per_iteration": 5.0}, "context": {"users": {"tenants": 3, "users_per_tenant": 5}}}, {"runner": {"times": 2000, "type": "constant", "concurrency": 75}, "args": {}, "sla": {"failure_rate": {"max": 0}, "max_avg_duration": 3.0, "max_seconds_per_iteration": 5.0}, "context": {"users": {"tenants": 3, "users_per_tenant": 5}}}, {"runner": {"times": 2000, "type": "constant", "concurrency": 76}, "args": {}, "sla": {"failure_rate": {"max": 0}, "max_avg_duration": 3.0, "max_seconds_per_iteration": 5.0}, "context": {"users": {"tenants": 3, "users_per_tenant": 5}}}, {"runner": {"times": 2000, "type": "constant", "concurrency": 77}, "args": {}, "sla": {"failure_rate": {"max": 0}, "max_avg_duration": 3.0, "max_seconds_per_iteration": 5.0}, "context": {"users": {"tenants": 3, "users_per_tenant": 5}}}, {"runner": {"times": 2000, "type": "constant", "concurrency": 78}, "args": {}, "sla": {"failure_rate": {"max": 0}, "max_avg_duration": 3.0, "max_seconds_per_iteration": 5.0}, "context": {"users": {"tenants": 3, "users_per_tenant": 5}}}, {"runner": {"times": 2000, "type": "constant", "concurrency": 79}, "args": {}, "sla": {"failure_rate": {"max": 0}, "max_avg_duration": 3.0, "max_seconds_per_iteration": 5.0}, "context": {"users": {"tenants": 3, "users_per_tenant": 5}}}, {"runner": {"times": 2000, "type": "constant", "concurrency": 80}, "args": {}, "sla": {"failure_rate": {"max": 0}, "max_avg_duration": 3.0, "max_seconds_per_iteration": 5.0}, "context": {"users": {"tenants": 3, "users_per_tenant": 5}}}, {"runner": {"times": 2000, "type": "constant", "concurrency": 81}, "args": {}, "sla": {"failure_rate": {"max": 0}, "max_avg_duration": 3.0, "max_seconds_per_iteration": 5.0}, "context": {"users": {"tenants": 3, "users_per_tenant": 5}}}, {"runner": {"times": 2000, "type": "constant", "concurrency": 82}, "args": {}, "sla": {"failure_rate": {"max": 0}, "max_avg_duration": 3.0, "max_seconds_per_iteration": 5.0}, "context": {"users": {"tenants": 3, "users_per_tenant": 5}}}, {"runner": {"times": 2000, "type": "constant", "concurrency": 83}, "args": {}, "sla": {"failure_rate": {"max": 0}, "max_avg_duration": 3.0, "max_seconds_per_iteration": 5.0}, "context": {"users": {"tenants": 3, "users_per_tenant": 5}}}, {"runner": {"times": 2000, "type": "constant", "concurrency": 84}, "args": {}, "sla": {"failure_rate": {"max": 0}, "max_avg_duration": 3.0, "max_seconds_per_iteration": 5.0}, "context": {"users": {"tenants": 3, "users_per_tenant": 5}}}, {"runner": {"times": 2000, "type": "constant", "concurrency": 85}, "args": {}, "sla": {"failure_rate": {"max": 0}, "max_avg_duration": 3.0, "max_seconds_per_iteration": 5.0}, "context": {"users": {"tenants": 3, "users_per_tenant": 5}}}, {"runner": {"times": 2000, "type": "constant", "concurrency": 86}, "args": {}, "sla": {"failure_rate": {"max": 0}, "max_avg_duration": 3.0, "max_seconds_per_iteration": 5.0}, "context": {"users": {"tenants": 3, "users_per_tenant": 5}}}, {"runner": {"times": 2000, "type": "constant", "concurrency": 87}, "args": {}, "sla": {"failure_rate": {"max": 0}, "max_avg_duration": 3.0, "max_seconds_per_iteration": 5.0}, "context": {"users": {"tenants": 3, "users_per_tenant": 5}}}, {"runner": {"times": 2000, "type": "constant", "concurrency": 88}, "args": {}, "sla": {"failure_rate": {"max": 0}, "max_avg_duration": 3.0, "max_seconds_per_iteration": 5.0}, "context": {"users": {"tenants": 3, "users_per_tenant": 5}}}, {"runner": {"times": 2000, "type": "constant", "concurrency": 89}, "args": {}, "sla": {"failure_rate": {"max": 0}, "max_avg_duration": 3.0, "max_seconds_per_iteration": 5.0}, "context": {"users": {"tenants": 3, "users_per_tenant": 5}}}, {"runner": {"times": 2000, "type": "constant", "concurrency": 90}, "args": {}, "sla": {"failure_rate": {"max": 0}, "max_avg_duration": 3.0, "max_seconds_per_iteration": 5.0}, "context": {"users": {"tenants": 3, "users_per_tenant": 5}}}, {"runner": {"times": 2000, "type": "constant", "concurrency": 91}, "args": {}, "sla": {"failure_rate": {"max": 0}, "max_avg_duration": 3.0, "max_seconds_per_iteration": 5.0}, "context": {"users": {"tenants": 3, "users_per_tenant": 5}}}, {"runner": {"times": 2000, "type": "constant", "concurrency": 92}, "args": {}, "sla": {"failure_rate": {"max": 0}, "max_avg_duration": 3.0, "max_seconds_per_iteration": 5.0}, "context": {"users": {"tenants": 3, "users_per_tenant": 5}}}, {"runner": {"times": 2000, "type": "constant", "concurrency": 93}, "args": {}, "sla": {"failure_rate": {"max": 0}, "max_avg_duration": 3.0, "max_seconds_per_iteration": 5.0}, "context": {"users": {"tenants": 3, "users_per_tenant": 5}}}, {"runner": {"times": 2000, "type": "constant", "concurrency": 94}, "args": {}, "sla": {"failure_rate": {"max": 0}, "max_avg_duration": 3.0, "max_seconds_per_iteration": 5.0}, "context": {"users": {"tenants": 3, "users_per_tenant": 5}}}, {"runner": {"times": 2000, "type": "constant", "concurrency": 95}, "args": {}, "sla": {"failure_rate": {"max": 0}, "max_avg_duration": 3.0, "max_seconds_per_iteration": 5.0}, "context": {"users": {"tenants": 3, "users_per_tenant": 5}}}, {"runner": {"times": 2000, "type": "constant", "concurrency": 96}, "args": {}, "sla": {"failure_rate": {"max": 0}, "max_avg_duration": 3.0, "max_seconds_per_iteration": 5.0}, "context": {"users": {"tenants": 3, "users_per_tenant": 5}}}, {"runner": {"times": 2000, "type": "constant", "concurrency": 97}, "args": {}, "sla": {"failure_rate": {"max": 0}, "max_avg_duration": 3.0, "max_seconds_per_iteration": 5.0}, "context": {"users": {"tenants": 3, "users_per_tenant": 5}}}, {"runner": {"times": 2000, "type": "constant", "concurrency": 98}, "args": {}, "sla": {"failure_rate": {"max": 0}, "max_avg_duration": 3.0, "max_seconds_per_iteration": 5.0}, "context": {"users": {"tenants": 3, "users_per_tenant": 5}}}, {"runner": {"times": 2000, "type": "constant", "concurrency": 99}, "args": {}, "sla": {"failure_rate": {"max": 0}, "max_avg_duration": 3.0, "max_seconds_per_iteration": 5.0}, "context": {"users": {"tenants": 3, "users_per_tenant": 5}}}, {"runner": {"times": 2000, "type": "constant", "concurrency": 100}, "args": {}, "sla": {"failure_rate": {"max": 0}, "max_avg_duration": 3.0, "max_seconds_per_iteration": 5.0}, "context": {"users": {"tenants": 3, "users_per_tenant": 5}}}]}