[
    {
        "hooks": [], 
        "created_at": "2017-17-02T01:48:53", 
        "load_duration": 163.57028102874756, 
        "result": [
            {
                "timestamp": 1487296136.304309, 
                "error": [], 
                "duration": 9.68103814125061, 
                "output": {
                    "additive": [], 
                    "complete": []
                }, 
                "idle_duration": 1.0, 
                "atomic_actions": {
                    "nova.boot_server": 9.967242002487183, 
                    "nova.show_server": 0.7135710716247559
                }
            }, 
            {
                "timestamp": 1487296136.305801, 
                "error": [], 
                "duration": 11.305890083312988, 
                "output": {
                    "additive": [], 
                    "complete": []
                }, 
                "idle_duration": 1.0, 
                "atomic_actions": {
                    "nova.boot_server": 11.606768131256104, 
                    "nova.show_server": 0.6989278793334961
                }
            }, 
            {
                "timestamp": 1487296136.309837, 
                "error": [], 
                "duration": 11.156078815460205, 
                "output": {
                    "additive": [], 
                    "complete": []
                }, 
                "idle_duration": 1.0, 
                "atomic_actions": {
                    "nova.boot_server": 11.486214876174927, 
                    "nova.show_server": 0.669691801071167
                }
            }, 
            {
                "timestamp": 1487296136.31159, 
                "error": [], 
                "duration": 9.860177993774414, 
                "output": {
                    "additive": [], 
                    "complete": []
                }, 
                "idle_duration": 1.0, 
                "atomic_actions": {
                    "nova.boot_server": 10.166542053222656, 
                    "nova.show_server": 0.6935019493103027
                }
            }, 
            {
                "timestamp": 1487296136.313444, 
                "error": [], 
                "duration": 9.644747018814087, 
                "output": {
                    "additive": [], 
                    "complete": []
                }, 
                "idle_duration": 1.0, 
                "atomic_actions": {
                    "nova.boot_server": 9.969413995742798, 
                    "nova.show_server": 0.6751561164855957
                }
            }, 
            {
                "timestamp": 1487296146.963151, 
                "error": [], 
                "duration": 11.253411054611206, 
                "output": {
                    "additive": [], 
                    "complete": []
                }, 
                "idle_duration": 1.0, 
                "atomic_actions": {
                    "nova.boot_server": 11.627380847930908, 
                    "nova.show_server": 0.6259369850158691
                }
            }, 
            {
                "timestamp": 1487296146.990233, 
                "error": [], 
                "duration": 11.403748989105225, 
                "output": {
                    "additive": [], 
                    "complete": []
                }, 
                "idle_duration": 1.0, 
                "atomic_actions": {
                    "nova.boot_server": 11.92902398109436, 
                    "nova.show_server": 0.4746248722076416
                }
            }, 
            {
                "timestamp": 1487296147.176516, 
                "error": [], 
                "duration": 11.223966836929321, 
                "output": {
                    "additive": [], 
                    "complete": []
                }, 
                "idle_duration": 1.0, 
                "atomic_actions": {
                    "nova.boot_server": 11.83288288116455, 
                    "nova.show_server": 0.39098286628723145
                }
            }, 
            {
                "timestamp": 1487296148.470832, 
                "error": [], 
                "duration": 10.420683860778809, 
                "output": {
                    "additive": [], 
                    "complete": []
                }, 
                "idle_duration": 1.0, 
                "atomic_actions": {
                    "nova.boot_server": 10.754415035247803, 
                    "nova.show_server": 0.6661689281463623
                }
            }, 
            {
                "timestamp": 1487296148.616306, 
                "error": [], 
                "duration": 11.788583993911743, 
                "output": {
                    "additive": [], 
                    "complete": []
                }, 
                "idle_duration": 1.0, 
                "atomic_actions": {
                    "nova.boot_server": 12.396399021148682, 
                    "nova.show_server": 0.3920919895172119
                }
            }, 
            {
                "timestamp": 1487296159.221415, 
                "error": [], 
                "duration": 9.691627979278564, 
                "output": {
                    "additive": [], 
                    "complete": []
                }, 
                "idle_duration": 1.0, 
                "atomic_actions": {
                    "nova.boot_server": 10.018983125686646, 
                    "nova.show_server": 0.6725449562072754
                }
            }, 
            {
                "timestamp": 1487296159.398475, 
                "error": [], 
                "duration": 11.277708053588867, 
                "output": {
                    "additive": [], 
                    "complete": []
                }, 
                "idle_duration": 1.0, 
                "atomic_actions": {
                    "nova.boot_server": 11.616844177246094, 
                    "nova.show_server": 0.6607639789581299
                }
            }, 
            {
                "timestamp": 1487296159.404941, 
                "error": [], 
                "duration": 10.089651823043823, 
                "output": {
                    "additive": [], 
                    "complete": []
                }, 
                "idle_duration": 1.0, 
                "atomic_actions": {
                    "nova.boot_server": 10.280503988265991, 
                    "nova.show_server": 0.8090429306030273
                }
            }, 
            {
                "timestamp": 1487296159.896204, 
                "error": [], 
                "duration": 10.492084980010986, 
                "output": {
                    "additive": [], 
                    "complete": []
                }, 
                "idle_duration": 1.0, 
                "atomic_actions": {
                    "nova.boot_server": 10.756355047225952, 
                    "nova.show_server": 0.7356290817260742
                }
            }, 
            {
                "timestamp": 1487296161.409737, 
                "error": [], 
                "duration": 10.003488779067993, 
                "output": {
                    "additive": [], 
                    "complete": []
                }, 
                "idle_duration": 1.0, 
                "atomic_actions": {
                    "nova.boot_server": 10.60481882095337, 
                    "nova.show_server": 0.3984110355377197
                }
            }, 
            {
                "timestamp": 1487296169.918094, 
                "error": [], 
                "duration": 9.337221145629883, 
                "output": {
                    "additive": [], 
                    "complete": []
                }, 
                "idle_duration": 1.0, 
                "atomic_actions": {
                    "nova.boot_server": 9.912253856658936, 
                    "nova.show_server": 0.4246799945831299
                }
            }, 
            {
                "timestamp": 1487296170.49936, 
                "error": [], 
                "duration": 10.99084997177124, 
                "output": {
                    "additive": [], 
                    "complete": []
                }, 
                "idle_duration": 1.0, 
                "atomic_actions": {
                    "nova.boot_server": 11.55346393585205, 
                    "nova.show_server": 0.43715381622314453
                }
            }, 
            {
                "timestamp": 1487296171.393276, 
                "error": [], 
                "duration": 13.113873958587646, 
                "output": {
                    "additive": [], 
                    "complete": []
                }, 
                "idle_duration": 1.0, 
                "atomic_actions": {
                    "nova.boot_server": 13.679116010665894, 
                    "nova.show_server": 0.43455004692077637
                }
            }, 
            {
                "timestamp": 1487296171.686711, 
                "error": [], 
                "duration": 13.312027931213379, 
                "output": {
                    "additive": [], 
                    "complete": []
                }, 
                "idle_duration": 1.0, 
                "atomic_actions": {
                    "nova.boot_server": 13.881757020950317, 
                    "nova.show_server": 0.43010807037353516
                }
            }, 
            {
                "timestamp": 1487296172.420448, 
                "error": [], 
                "duration": 10.078300952911377, 
                "output": {
                    "additive": [], 
                    "complete": []
                }, 
                "idle_duration": 1.0, 
                "atomic_actions": {
                    "nova.boot_server": 10.795743942260742, 
                    "nova.show_server": 0.28241801261901855
                }
            }, 
            {
                "timestamp": 1487296180.263771, 
                "error": [], 
                "duration": 9.381484985351562, 
                "output": {
                    "additive": [], 
                    "complete": []
                }, 
                "idle_duration": 1.0, 
                "atomic_actions": {
                    "nova.boot_server": 9.974189043045044, 
                    "nova.show_server": 0.40720510482788086
                }
            }, 
            {
                "timestamp": 1487296182.498346, 
                "error": [], 
                "duration": 11.17254900932312, 
                "output": {
                    "additive": [], 
                    "complete": []
                }, 
                "idle_duration": 1.0, 
                "atomic_actions": {
                    "nova.boot_server": 11.684851884841919, 
                    "nova.show_server": 0.48757505416870117
                }
            }, 
            {
                "timestamp": 1487296183.503403, 
                "error": [], 
                "duration": 10.272951126098633, 
                "output": {
                    "additive": [], 
                    "complete": []
                }, 
                "idle_duration": 1.0, 
                "atomic_actions": {
                    "nova.boot_server": 10.584473133087158, 
                    "nova.show_server": 0.6883718967437744
                }
            }, 
            {
                "timestamp": 1487296185.514235, 
                "error": [], 
                "duration": 11.386359930038452, 
                "output": {
                    "additive": [], 
                    "complete": []
                }, 
                "idle_duration": 1.0, 
                "atomic_actions": {
                    "nova.boot_server": 11.946885108947754, 
                    "nova.show_server": 0.4393320083618164
                }
            }, 
            {
                "timestamp": 1487296186.003601, 
                "error": [], 
                "duration": 11.698078870773315, 
                "output": {
                    "additive": [], 
                    "complete": []
                }, 
                "idle_duration": 1.0, 
                "atomic_actions": {
                    "nova.boot_server": 11.894593000411987, 
                    "nova.show_server": 0.803380012512207
                }
            }, 
            {
                "timestamp": 1487296190.649953, 
                "error": [], 
                "duration": 12.081329107284546, 
                "output": {
                    "additive": [], 
                    "complete": []
                }, 
                "idle_duration": 1.0, 
                "atomic_actions": {
                    "nova.boot_server": 12.383094072341919, 
                    "nova.show_server": 0.6981279850006104
                }
            }, 
            {
                "timestamp": 1487296194.675926, 
                "error": [], 
                "duration": 10.195717096328735, 
                "output": {
                    "additive": [], 
                    "complete": []
                }, 
                "idle_duration": 1.0, 
                "atomic_actions": {
                    "nova.boot_server": 10.798671007156372, 
                    "nova.show_server": 0.3969569206237793
                }
            }, 
            {
                "timestamp": 1487296194.781289, 
                "error": [], 
                "duration": 10.042367935180664, 
                "output": {
                    "additive": [], 
                    "complete": []
                }, 
                "idle_duration": 1.0, 
                "atomic_actions": {
                    "nova.boot_server": 10.226102828979492, 
                    "nova.show_server": 0.8161568641662598
                }
            }, 
            {
                "timestamp": 1487296197.905047, 
                "error": [], 
                "duration": 11.70273208618164, 
                "output": {
                    "additive": [], 
                    "complete": []
                }, 
                "idle_duration": 1.0, 
                "atomic_actions": {
                    "nova.boot_server": 11.990255117416382, 
                    "nova.show_server": 0.7123911380767822
                }
            }, 
            {
                "timestamp": 1487296198.706987, 
                "error": [], 
                "duration": 9.715076208114624, 
                "output": {
                    "additive": [], 
                    "complete": []
                }, 
                "idle_duration": 1.0, 
                "atomic_actions": {
                    "nova.boot_server": 10.306921005249023, 
                    "nova.show_server": 0.40798187255859375
                }
            }, 
            {
                "timestamp": 1487296203.736029, 
                "error": [], 
                "duration": 9.246829986572266, 
                "output": {
                    "additive": [], 
                    "complete": []
                }, 
                "idle_duration": 1.0, 
                "atomic_actions": {
                    "nova.boot_server": 9.553914070129395, 
                    "nova.show_server": 0.6928188800811768
                }
            }, 
            {
                "timestamp": 1487296205.828603, 
                "error": [], 
                "duration": 11.941858053207397, 
                "output": {
                    "additive": [], 
                    "complete": []
                }, 
                "idle_duration": 1.0, 
                "atomic_actions": {
                    "nova.boot_server": 12.231893062591553, 
                    "nova.show_server": 0.7098591327667236
                }
            }, 
            {
                "timestamp": 1487296205.876439, 
                "error": [], 
                "duration": 9.4947509765625, 
                "output": {
                    "additive": [], 
                    "complete": []
                }, 
                "idle_duration": 1.0, 
                "atomic_actions": {
                    "nova.boot_server": 10.050289154052734, 
                    "nova.show_server": 0.4443690776824951
                }
            }, 
            {
                "timestamp": 1487296209.428295, 
                "error": [], 
                "duration": 11.807125091552734, 
                "output": {
                    "additive": [], 
                    "complete": []
                }, 
                "idle_duration": 1.0, 
                "atomic_actions": {
                    "nova.boot_server": 12.402700901031494, 
                    "nova.show_server": 0.4043159484863281
                }
            }, 
            {
                "timestamp": 1487296210.612291, 
                "error": [], 
                "duration": 8.794995784759521, 
                "output": {
                    "additive": [], 
                    "complete": []
                }, 
                "idle_duration": 1.0, 
                "atomic_actions": {
                    "nova.boot_server": 9.357785940170288, 
                    "nova.show_server": 0.4371170997619629
                }
            }, 
            {
                "timestamp": 1487296213.987717, 
                "error": [], 
                "duration": 10.623444080352783, 
                "output": {
                    "additive": [], 
                    "complete": []
                }, 
                "idle_duration": 1.0, 
                "atomic_actions": {
                    "nova.boot_server": 10.859523057937622, 
                    "nova.show_server": 0.7638230323791504
                }
            }, 
            {
                "timestamp": 1487296216.37617, 
                "error": [], 
                "duration": 11.38730502128601, 
                "output": {
                    "additive": [], 
                    "complete": []
                }, 
                "idle_duration": 1.0, 
                "atomic_actions": {
                    "nova.boot_server": 11.978100061416626, 
                    "nova.show_server": 0.40911197662353516
                }
            }, 
            {
                "timestamp": 1487296218.774466, 
                "error": [], 
                "duration": 11.404742956161499, 
                "output": {
                    "additive": [], 
                    "complete": []
                }, 
                "idle_duration": 1.0, 
                "atomic_actions": {
                    "nova.boot_server": 11.681124925613403, 
                    "nova.show_server": 0.7235209941864014
                }
            }, 
            {
                "timestamp": 1487296220.411913, 
                "error": [], 
                "duration": 10.160837173461914, 
                "output": {
                    "additive": [], 
                    "complete": []
                }, 
                "idle_duration": 1.0, 
                "atomic_actions": {
                    "nova.boot_server": 10.513185977935791, 
                    "nova.show_server": 0.6475551128387451
                }
            }, 
            {
                "timestamp": 1487296222.240606, 
                "error": [], 
                "duration": 11.741575956344604, 
                "output": {
                    "additive": [], 
                    "complete": []
                }, 
                "idle_duration": 1.0, 
                "atomic_actions": {
                    "nova.boot_server": 12.106957912445068, 
                    "nova.show_server": 0.6345160007476807
                }
            }, 
            {
                "timestamp": 1487296225.61603, 
                "error": [], 
                "duration": 10.30413007736206, 
                "output": {
                    "additive": [], 
                    "complete": []
                }, 
                "idle_duration": 1.0, 
                "atomic_actions": {
                    "nova.boot_server": 10.60179877281189, 
                    "nova.show_server": 0.7022249698638916
                }
            }, 
            {
                "timestamp": 1487296228.768254, 
                "error": [], 
                "duration": 10.92896294593811, 
                "output": {
                    "additive": [], 
                    "complete": []
                }, 
                "idle_duration": 1.0, 
                "atomic_actions": {
                    "nova.boot_server": 11.440603971481323, 
                    "nova.show_server": 0.48822617530822754
                }
            }, 
            {
                "timestamp": 1487296231.184136, 
                "error": [], 
                "duration": 12.02759313583374, 
                "output": {
                    "additive": [], 
                    "complete": []
                }, 
                "idle_duration": 1.0, 
                "atomic_actions": {
                    "nova.boot_server": 12.602082967758179, 
                    "nova.show_server": 0.42536497116088867
                }
            }, 
            {
                "timestamp": 1487296231.576778, 
                "error": [], 
                "duration": 9.413527965545654, 
                "output": {
                    "additive": [], 
                    "complete": []
                }, 
                "idle_duration": 1.0, 
                "atomic_actions": {
                    "nova.boot_server": 9.647345066070557, 
                    "nova.show_server": 0.7660870552062988
                }
            }, 
            {
                "timestamp": 1487296234.987245, 
                "error": [], 
                "duration": 9.534749031066895, 
                "output": {
                    "additive": [], 
                    "complete": []
                }, 
                "idle_duration": 1.0, 
                "atomic_actions": {
                    "nova.boot_server": 10.127442121505737, 
                    "nova.show_server": 0.40718603134155273
                }
            }, 
            {
                "timestamp": 1487296236.925136, 
                "error": [], 
                "duration": 9.157557010650635, 
                "output": {
                    "additive": [], 
                    "complete": []
                }, 
                "idle_duration": 1.0, 
                "atomic_actions": {
                    "nova.boot_server": 9.86482310295105, 
                    "nova.show_server": 0.2925879955291748
                }
            }, 
            {
                "timestamp": 1487296240.70217, 
                "error": [], 
                "duration": 11.665846109390259, 
                "output": {
                    "additive": [], 
                    "complete": []
                }, 
                "idle_duration": 1.0, 
                "atomic_actions": {
                    "nova.boot_server": 11.915272951126099, 
                    "nova.show_server": 0.7504339218139648
                }
            }, 
            {
                "timestamp": 1487296241.995164, 
                "error": [], 
                "duration": 9.530318975448608, 
                "output": {
                    "additive": [], 
                    "complete": []
                }, 
                "idle_duration": 1.0, 
                "atomic_actions": {
                    "nova.boot_server": 10.068687915802002, 
                    "nova.show_server": 0.46149706840515137
                }
            }, 
            {
                "timestamp": 1487296244.217678, 
                "error": [], 
                "duration": 9.838188886642456, 
                "output": {
                    "additive": [], 
                    "complete": []
                }, 
                "idle_duration": 1.0, 
                "atomic_actions": {
                    "nova.boot_server": 10.084623098373413, 
                    "nova.show_server": 0.7534580230712891
                }
            }, 
            {
                "timestamp": 1487296245.527629, 
                "error": [], 
                "duration": 11.14198899269104, 
                "output": {
                    "additive": [], 
                    "complete": []
                }, 
                "idle_duration": 1.0, 
                "atomic_actions": {
                    "nova.boot_server": 11.45746922492981, 
                    "nova.show_server": 0.6844179630279541
                }
            }, 
            {
                "timestamp": 1487296247.088356, 
                "error": [], 
                "duration": 10.162137985229492, 
                "output": {
                    "additive": [], 
                    "complete": []
                }, 
                "idle_duration": 1.0, 
                "atomic_actions": {
                    "nova.boot_server": 10.498667001724243, 
                    "nova.show_server": 0.6633529663085938
                }
            }, 
            {
                "timestamp": 1487296252.531334, 
                "error": [], 
                "duration": 10.167538166046143, 
                "output": {
                    "additive": [], 
                    "complete": []
                }, 
                "idle_duration": 1.0, 
                "atomic_actions": {
                    "nova.boot_server": 10.992713928222656, 
                    "nova.show_server": 0.1747291088104248
                }
            }, 
            {
                "timestamp": 1487296253.373032, 
                "error": [], 
                "duration": 9.934249877929688, 
                "output": {
                    "additive": [], 
                    "complete": []
                }, 
                "idle_duration": 1.0, 
                "atomic_actions": {
                    "nova.boot_server": 10.522784948348999, 
                    "nova.show_server": 0.4113469123840332
                }
            }, 
            {
                "timestamp": 1487296255.06062, 
                "error": [], 
                "duration": 10.553056001663208, 
                "output": {
                    "additive": [], 
                    "complete": []
                }, 
                "idle_duration": 1.0, 
                "atomic_actions": {
                    "nova.boot_server": 10.720850944519043, 
                    "nova.show_server": 0.8321020603179932
                }
            }, 
            {
                "timestamp": 1487296257.674484, 
                "error": [], 
                "duration": 9.917241096496582, 
                "output": {
                    "additive": [], 
                    "complete": []
                }, 
                "idle_duration": 1.0, 
                "atomic_actions": {
                    "nova.boot_server": 10.225741147994995, 
                    "nova.show_server": 0.6913950443267822
                }
            }, 
            {
                "timestamp": 1487296258.255321, 
                "error": [], 
                "duration": 10.578212022781372, 
                "output": {
                    "additive": [], 
                    "complete": []
                }, 
                "idle_duration": 1.0, 
                "atomic_actions": {
                    "nova.boot_server": 10.983459949493408, 
                    "nova.show_server": 0.5946409702301025
                }
            }, 
            {
                "timestamp": 1487296263.703615, 
                "error": [], 
                "duration": 11.595371961593628, 
                "output": {
                    "additive": [], 
                    "complete": []
                }, 
                "idle_duration": 1.0, 
                "atomic_actions": {
                    "nova.boot_server": 12.188199996948242, 
                    "nova.show_server": 0.4070861339569092
                }
            }, 
            {
                "timestamp": 1487296264.311283, 
                "error": [], 
                "duration": 11.728351831436157, 
                "output": {
                    "additive": [], 
                    "complete": []
                }, 
                "idle_duration": 1.0, 
                "atomic_actions": {
                    "nova.boot_server": 12.076709032058716, 
                    "nova.show_server": 0.6515488624572754
                }
            }, 
            {
                "timestamp": 1487296266.618313, 
                "error": [], 
                "duration": 11.457988977432251, 
                "output": {
                    "additive": [], 
                    "complete": []
                }, 
                "idle_duration": 1.0, 
                "atomic_actions": {
                    "nova.boot_server": 11.781434059143066, 
                    "nova.show_server": 0.6764590740203857
                }
            }, 
            {
                "timestamp": 1487296268.596665, 
                "error": [], 
                "duration": 10.968994140625, 
                "output": {
                    "additive": [], 
                    "complete": []
                }, 
                "idle_duration": 1.0, 
                "atomic_actions": {
                    "nova.boot_server": 11.209342002868652, 
                    "nova.show_server": 0.7594139575958252
                }
            }, 
            {
                "timestamp": 1487296269.838245, 
                "error": [], 
                "duration": 11.801773071289062, 
                "output": {
                    "additive": [], 
                    "complete": []
                }, 
                "idle_duration": 1.0, 
                "atomic_actions": {
                    "nova.boot_server": 12.39054799079895, 
                    "nova.show_server": 0.4111289978027344
                }
            }, 
            {
                "timestamp": 1487296276.304056, 
                "error": [], 
                "duration": 11.415460109710693, 
                "output": {
                    "additive": [], 
                    "complete": []
                }, 
                "idle_duration": 1.0, 
                "atomic_actions": {
                    "nova.boot_server": 11.779486894607544, 
                    "nova.show_server": 0.6358599662780762
                }
            }, 
            {
                "timestamp": 1487296277.044392, 
                "error": [], 
                "duration": 10.025107860565186, 
                "output": {
                    "additive": [], 
                    "complete": []
                }, 
                "idle_duration": 1.0, 
                "atomic_actions": {
                    "nova.boot_server": 10.534221887588501, 
                    "nova.show_server": 0.49077296257019043
                }
            }, 
            {
                "timestamp": 1487296279.080389, 
                "error": [], 
                "duration": 12.764595985412598, 
                "output": {
                    "additive": [], 
                    "complete": []
                }, 
                "idle_duration": 1.0, 
                "atomic_actions": {
                    "nova.boot_server": 12.72598910331726, 
                    "nova.show_server": 1.0385100841522217
                }
            }, 
            {
                "timestamp": 1487296280.572975, 
                "error": [], 
                "duration": 11.544900178909302, 
                "output": {
                    "additive": [], 
                    "complete": []
                }, 
                "idle_duration": 1.0, 
                "atomic_actions": {
                    "nova.boot_server": 11.992598056793213, 
                    "nova.show_server": 0.5521419048309326
                }
            }, 
            {
                "timestamp": 1487296282.644677, 
                "error": [], 
                "duration": 17.229912996292114, 
                "output": {
                    "additive": [], 
                    "complete": []
                }, 
                "idle_duration": 1.0, 
                "atomic_actions": {
                    "nova.boot_server": 17.541582107543945, 
                    "nova.show_server": 0.6881639957427979
                }
            }, 
            {
                "timestamp": 1487296288.074444, 
                "error": [
                    "GetResourceErrorStatus", 
                    "Resource <Server: s_rally_7a572ab0_RryE3ObP> has ERROR status.\nFault: {u'message': u'No valid host was found. There are not enough hosts available.', u'code': 500, u'created': u'2017-02-17T01:51:31Z'}", 
                    "Traceback (most recent call last):\n  File \"/usr/local/lib/python2.7/dist-packages/rally/task/runner.py\", line 72, in _run_scenario_once\n    getattr(scenario_inst, method_name)(**scenario_kwargs)\n  File \"/usr/local/lib/python2.7/dist-packages/rally/plugins/openstack/scenarios/nova/servers.py\", line 854, in run\n    server = self._boot_server(image, flavor, **kwargs)\n  File \"/usr/local/lib/python2.7/dist-packages/rally/task/atomic.py\", line 84, in func_atomic_actions\n    f = func(self, *args, **kwargs)\n  File \"/usr/local/lib/python2.7/dist-packages/rally/plugins/openstack/scenarios/nova/utils.py\", line 146, in _boot_server\n    check_interval=CONF.benchmark.nova_server_boot_poll_interval\n  File \"/usr/local/lib/python2.7/dist-packages/rally/task/utils.py\", line 214, in wait_for_status\n    resource = update_resource(resource)\n  File \"/usr/local/lib/python2.7/dist-packages/rally/task/utils.py\", line 90, in _get_from_manager\n    fault=getattr(res, \"fault\", \"n/a\"))\nGetResourceErrorStatus: Resource <Server: s_rally_7a572ab0_RryE3ObP> has ERROR status.\nFault: {u'message': u'No valid host was found. There are not enough hosts available.', u'code': 500, u'created': u'2017-02-17T01:51:31Z'}\n"
                ], 
                "duration": 4.0921478271484375, 
                "output": {
                    "additive": [], 
                    "complete": []
                }, 
                "idle_duration": 1.0, 
                "atomic_actions": {
                    "nova.boot_server": 5.092077970504761
                }
            }, 
            {
                "timestamp": 1487296288.724302, 
                "error": [
                    "GetResourceErrorStatus", 
                    "Resource <Server: s_rally_7a572ab0_kE7D42GZ> has ERROR status.\nFault: {u'message': u'No valid host was found. There are not enough hosts available.', u'code': 500, u'created': u'2017-02-17T01:51:32Z'}", 
                    "Traceback (most recent call last):\n  File \"/usr/local/lib/python2.7/dist-packages/rally/task/runner.py\", line 72, in _run_scenario_once\n    getattr(scenario_inst, method_name)(**scenario_kwargs)\n  File \"/usr/local/lib/python2.7/dist-packages/rally/plugins/openstack/scenarios/nova/servers.py\", line 854, in run\n    server = self._boot_server(image, flavor, **kwargs)\n  File \"/usr/local/lib/python2.7/dist-packages/rally/task/atomic.py\", line 84, in func_atomic_actions\n    f = func(self, *args, **kwargs)\n  File \"/usr/local/lib/python2.7/dist-packages/rally/plugins/openstack/scenarios/nova/utils.py\", line 146, in _boot_server\n    check_interval=CONF.benchmark.nova_server_boot_poll_interval\n  File \"/usr/local/lib/python2.7/dist-packages/rally/task/utils.py\", line 214, in wait_for_status\n    resource = update_resource(resource)\n  File \"/usr/local/lib/python2.7/dist-packages/rally/task/utils.py\", line 90, in _get_from_manager\n    fault=getattr(res, \"fault\", \"n/a\"))\nGetResourceErrorStatus: Resource <Server: s_rally_7a572ab0_kE7D42GZ> has ERROR status.\nFault: {u'message': u'No valid host was found. There are not enough hosts available.', u'code': 500, u'created': u'2017-02-17T01:51:32Z'}\n"
                ], 
                "duration": 4.7632739543914795, 
                "output": {
                    "additive": [], 
                    "complete": []
                }, 
                "idle_duration": 1.0, 
                "atomic_actions": {
                    "nova.boot_server": 5.763221025466919
                }
            }, 
            {
                "timestamp": 1487296292.848739, 
                "error": [
                    "GetResourceErrorStatus", 
                    "Resource <Server: s_rally_7a572ab0_j0hMZzui> has ERROR status.\nFault: {u'message': u'No valid host was found. There are not enough hosts available.', u'code': 500, u'created': u'2017-02-17T01:51:36Z'}", 
                    "Traceback (most recent call last):\n  File \"/usr/local/lib/python2.7/dist-packages/rally/task/runner.py\", line 72, in _run_scenario_once\n    getattr(scenario_inst, method_name)(**scenario_kwargs)\n  File \"/usr/local/lib/python2.7/dist-packages/rally/plugins/openstack/scenarios/nova/servers.py\", line 854, in run\n    server = self._boot_server(image, flavor, **kwargs)\n  File \"/usr/local/lib/python2.7/dist-packages/rally/task/atomic.py\", line 84, in func_atomic_actions\n    f = func(self, *args, **kwargs)\n  File \"/usr/local/lib/python2.7/dist-packages/rally/plugins/openstack/scenarios/nova/utils.py\", line 146, in _boot_server\n    check_interval=CONF.benchmark.nova_server_boot_poll_interval\n  File \"/usr/local/lib/python2.7/dist-packages/rally/task/utils.py\", line 214, in wait_for_status\n    resource = update_resource(resource)\n  File \"/usr/local/lib/python2.7/dist-packages/rally/task/utils.py\", line 90, in _get_from_manager\n    fault=getattr(res, \"fault\", \"n/a\"))\nGetResourceErrorStatus: Resource <Server: s_rally_7a572ab0_j0hMZzui> has ERROR status.\nFault: {u'message': u'No valid host was found. There are not enough hosts available.', u'code': 500, u'created': u'2017-02-17T01:51:36Z'}\n"
                ], 
                "duration": 3.5734500885009766, 
                "output": {
                    "additive": [], 
                    "complete": []
                }, 
                "idle_duration": 1.0, 
                "atomic_actions": {
                    "nova.boot_server": 4.573400020599365
                }
            }, 
            {
                "timestamp": 1487296293.122547, 
                "error": [
                    "GetResourceErrorStatus", 
                    "Resource <Server: s_rally_7a572ab0_deKtaYxN> has ERROR status.\nFault: {u'message': u'No valid host was found. There are not enough hosts available.', u'code': 500, u'created': u'2017-02-17T01:51:36Z'}", 
                    "Traceback (most recent call last):\n  File \"/usr/local/lib/python2.7/dist-packages/rally/task/runner.py\", line 72, in _run_scenario_once\n    getattr(scenario_inst, method_name)(**scenario_kwargs)\n  File \"/usr/local/lib/python2.7/dist-packages/rally/plugins/openstack/scenarios/nova/servers.py\", line 854, in run\n    server = self._boot_server(image, flavor, **kwargs)\n  File \"/usr/local/lib/python2.7/dist-packages/rally/task/atomic.py\", line 84, in func_atomic_actions\n    f = func(self, *args, **kwargs)\n  File \"/usr/local/lib/python2.7/dist-packages/rally/plugins/openstack/scenarios/nova/utils.py\", line 146, in _boot_server\n    check_interval=CONF.benchmark.nova_server_boot_poll_interval\n  File \"/usr/local/lib/python2.7/dist-packages/rally/task/utils.py\", line 214, in wait_for_status\n    resource = update_resource(resource)\n  File \"/usr/local/lib/python2.7/dist-packages/rally/task/utils.py\", line 90, in _get_from_manager\n    fault=getattr(res, \"fault\", \"n/a\"))\nGetResourceErrorStatus: Resource <Server: s_rally_7a572ab0_deKtaYxN> has ERROR status.\nFault: {u'message': u'No valid host was found. There are not enough hosts available.', u'code': 500, u'created': u'2017-02-17T01:51:36Z'}\n"
                ], 
                "duration": 3.940491199493408, 
                "output": {
                    "additive": [], 
                    "complete": []
                }, 
                "idle_duration": 1.0, 
                "atomic_actions": {
                    "nova.boot_server": 4.940441846847534
                }
            }, 
            {
                "timestamp": 1487296293.17471, 
                "error": [
                    "GetResourceErrorStatus", 
                    "Resource <Server: s_rally_7a572ab0_gQbQk2ru> has ERROR status.\nFault: {u'message': u'No valid host was found. There are not enough hosts available.', u'code': 500, u'created': u'2017-02-17T01:51:36Z'}", 
                    "Traceback (most recent call last):\n  File \"/usr/local/lib/python2.7/dist-packages/rally/task/runner.py\", line 72, in _run_scenario_once\n    getattr(scenario_inst, method_name)(**scenario_kwargs)\n  File \"/usr/local/lib/python2.7/dist-packages/rally/plugins/openstack/scenarios/nova/servers.py\", line 854, in run\n    server = self._boot_server(image, flavor, **kwargs)\n  File \"/usr/local/lib/python2.7/dist-packages/rally/task/atomic.py\", line 84, in func_atomic_actions\n    f = func(self, *args, **kwargs)\n  File \"/usr/local/lib/python2.7/dist-packages/rally/plugins/openstack/scenarios/nova/utils.py\", line 146, in _boot_server\n    check_interval=CONF.benchmark.nova_server_boot_poll_interval\n  File \"/usr/local/lib/python2.7/dist-packages/rally/task/utils.py\", line 214, in wait_for_status\n    resource = update_resource(resource)\n  File \"/usr/local/lib/python2.7/dist-packages/rally/task/utils.py\", line 90, in _get_from_manager\n    fault=getattr(res, \"fault\", \"n/a\"))\nGetResourceErrorStatus: Resource <Server: s_rally_7a572ab0_gQbQk2ru> has ERROR status.\nFault: {u'message': u'No valid host was found. There are not enough hosts available.', u'code': 500, u'created': u'2017-02-17T01:51:36Z'}\n"
                ], 
                "duration": 3.6270909309387207, 
                "output": {
                    "additive": [], 
                    "complete": []
                }, 
                "idle_duration": 1.0, 
                "atomic_actions": {
                    "nova.boot_server": 4.627023935317993
                }
            }
        ], 
        "key": {
            "kw": {
                "runner": {
                    "times": 100, 
                    "type": "constant", 
                    "concurrency": 5
                }, 
                "hooks": [], 
                "args": {
                    "flavor": {
                        "name": "m1.medium"
                    }, 
                    "image": {
                        "name": "^cirros.*-disk$"
                    }
                }, 
                "sla": {
                    "max_seconds_per_iteration": 120.0, 
                    "failure_rate": {
                        "max": 0
                    }, 
                    "max_avg_duration": 60.0
                }, 
                "context": {
                    "quotas": {
                        "nova": {
                            "server_groups": -1, 
                            "injected_file_content_bytes": -1, 
                            "cores": -1, 
                            "floating_ips": -1, 
                            "security_group_rules": -1, 
                            "metadata_items": -1, 
                            "instances": -1, 
                            "key_pairs": -1, 
                            "injected_files": -1, 
                            "fixed_ips": -1, 
                            "security_groups": -1, 
                            "injected_file_path_bytes": -1, 
                            "ram": -1, 
                            "server_group_members": -1
                        }
                    }, 
                    "users": {
                        "tenants": 3, 
                        "users_per_tenant": 5
                    }
                }
            }, 
            "name": "NovaServers.boot_and_show_server", 
            "pos": 0
        }, 
        "full_duration": 206.5263237953186, 
        "sla": [
            {
                "criterion": "max_seconds_per_iteration", 
                "detail": "Maximum seconds per iteration 17.23s <= 120.00s - Passed", 
                "success": true
            }, 
            {
                "criterion": "failure_rate", 
                "detail": "Failure rate criteria 0.00% <= 7.04% <= 0.00% - Failed", 
                "success": false
            }, 
            {
                "criterion": "max_avg_duration", 
                "detail": "Average duration of one iteration 10.84s <= 60.00s - Passed", 
                "success": true
            }, 
            {
                "criterion": "aborted_on_sla", 
                "detail": "Task was aborted due to SLA failure(s).", 
                "success": false
            }
        ]
    }
]
